setup.py
jgpycshare/DateTime.py
jgpycshare/JsonTools.py
jgpycshare/LogTools.py
jgpycshare/StringTools.py
jgpycshare/__init__.py
jgpycshare/filetools.py
jgpycshare/httptools.py
jgpycshare/jgencode.py
jgpycshare/mysqlite.py
jgpycshare/mysqltools.py
jgpycshare/times.py
jgpycshare.egg-info/PKG-INFO
jgpycshare.egg-info/SOURCES.txt
jgpycshare.egg-info/dependency_links.txt
jgpycshare.egg-info/requires.txt
jgpycshare.egg-info/top_level.txt
jslib/__init__.py
jslib/apitools.py
jslib/logtool.py