Metadata-Version: 1.0
Name: jgpycshare
Version: 1.8.8
Summary: jgpycshare
Home-page: UNKNOWN
Author: jiegemena
Author-email: jiegemena@outlook.com
License: UNKNOWN
Platform: UNKNOWN
